[{"created_at":"Thu Jan 19 15:29:31 +0000 2017","id":822103702337191936,"id_str":"822103702337191936","text":"A new favorite: Fading by <a href="http://www.twitter.com/">@</a>___PRAYER https:\/\/t.co\/LULrzM7eJr on <a target="_new" href="http://twitter.com/search?q=SoundCloud">#SoundCloud</a>","truncated":false,"entities":{"hashtags":[{"text":"SoundCloud","indices":[64,75]}],"symbols":[],"user_mentions":[{"screen_name":"___PRAYER","name":"Prayer","id":2977016789,"id_str":"2977016789","indices":[26,36]}],"urls":[{"url":"https:\/\/t.co\/LULrzM7eJr","expanded_url":"https:\/\/soundcloud.com\/prayerproduction\/fading-2","display_url":"soundcloud.com\/prayerproducti\u2026","indices":[37,60]}]},"source":"\u003ca href=\"http:\/\/soundcloud.com\" rel=\"nofollow\"\u003eSoundCloud\u003c\/a\u003e","in_reply_to_status_id":null,"in_reply_to_status_id_str":null,"in_reply_to_user_id":null,"in_reply_to_user_id_str":null,"in_reply_to_screen_name":null,"user":{"id":104534121,"id_str":"104534121","name":"Insert","screen_name":"WeAreInsert","location":"London","description":"Insert is a virtual platform which uses audio, visual & textual formats to push and contextualise select areas of underground music. <a href="http://www.twitter.com/VICE">@VICE</a> | <a href="http://www.twitter.com/NTSlive">@NTSlive</a>","url":"https:\/\/t.co\/06GZVcXiJV","entities":{"url":{"urls":[{"url":"https:\/\/t.co\/06GZVcXiJV","expanded_url":"http:\/\/weareinsert.com","display_url":"weareinsert.com","indices":[0,23]}]},"description":{"urls":[]}},"protected":false,"followers_count":1328,"friends_count":845,"listed_count":23,"created_at":"Wed Jan 13 16:35:55 +0000 2010","favourites_count":1123,"utc_offset":0,"time_zone":"London","geo_enabled":true,"verified":false,"statuses_count":4780,"lang":"en","contributors_enabled":false,"is_translator":false,"is_translation_enabled":false,"profile_background_color":"000000","profile_background_image_url":"http:\/\/pbs.twimg.com\/profile_background_images\/551739826647490560\/p5wNFMMU.jpeg","profile_background_image_url_https":"https:\/\/pbs.twimg.com\/profile_background_images\/551739826647490560\/p5wNFMMU.jpeg","profile_background_tile":true,"profile_image_url":"http:\/\/pbs.twimg.com\/profile_images\/620540450500419584\/HHkre3eX_normal.jpg","profile_image_url_https":"https:\/\/pbs.twimg.com\/profile_images\/620540450500419584\/HHkre3eX_normal.jpg","profile_banner_url":"https:\/\/pbs.twimg.com\/profile_banners\/104534121\/1420379970","profile_link_color":"000000","profile_sidebar_border_color":"FFFFFF","profile_sidebar_fill_color":"E6F6F9","profile_text_color":"333333","profile_use_background_image":true,"has_extended_profile":false,"default_profile":false,"default_profile_image":false,"following":false,"follow_request_sent":false,"notifications":false,"translator_type":"none"},"geo":null,"coordinates":null,"place":null,"contributors":null,"is_quote_status":false,"retweet_count":1,"favorite_count":0,"favorited":false,"retweeted":false,"possibly_sensitive":false,"lang":"en"},{"created_at":"Thu Jan 19 14:33:44 +0000 2017","id":822089665339604993,"id_str":"822089665339604993","text":"A new favorite: LUZ (lowkey) by <a href="http://www.twitter.com/MartelFerdan">@MartelFerdan</a> https:\/\/t.co\/3iTZVihHCd on <a target="_new" href="http://twitter.com/search?q=SoundCloud">#SoundCloud</a>","truncated":false,"entities":{"hashtags":[{"text":"SoundCloud","indices":[73,84]}],"symbols":[],"user_mentions":[{"screen_name":"MartelFerdan","name":"Martel Ferdan","id":461577823,"id_str":"461577823","indices":[32,45]}],"urls":[{"url":"https:\/\/t.co\/3iTZVihHCd","expanded_url":"https:\/\/soundcloud.com\/martelferdan\/luz-lowkey","display_url":"soundcloud.com\/martelferdan\/l\u2026","indices":[46,69]}]},"source":"\u003ca href=\"http:\/\/soundcloud.com\" rel=\"nofollow\"\u003eSoundCloud\u003c\/a\u003e","in_reply_to_status_id":null,"in_reply_to_status_id_str":null,"in_reply_to_user_id":null,"in_reply_to_user_id_str":null,"in_reply_to_screen_name":null,"user":{"id":104534121,"id_str":"104534121","name":"Insert","screen_name":"WeAreInsert","location":"London","description":"Insert is a virtual platform which uses audio, visual & textual formats to push and contextualise select areas of underground music. <a href="http://www.twitter.com/VICE">@VICE</a> | <a href="http://www.twitter.com/NTSlive">@NTSlive</a>","url":"https:\/\/t.co\/06GZVcXiJV","entities":{"url":{"urls":[{"url":"https:\/\/t.co\/06GZVcXiJV","expanded_url":"http:\/\/weareinsert.com","display_url":"weareinsert.com","indices":[0,23]}]},"description":{"urls":[]}},"protected":false,"followers_count":1328,"friends_count":845,"listed_count":23,"created_at":"Wed Jan 13 16:35:55 +0000 2010","favourites_count":1123,"utc_offset":0,"time_zone":"London","geo_enabled":true,"verified":false,"statuses_count":4780,"lang":"en","contributors_enabled":false,"is_translator":false,"is_translation_enabled":false,"profile_background_color":"000000","profile_background_image_url":"http:\/\/pbs.twimg.com\/profile_background_images\/551739826647490560\/p5wNFMMU.jpeg","profile_background_image_url_https":"https:\/\/pbs.twimg.com\/profile_background_images\/551739826647490560\/p5wNFMMU.jpeg","profile_background_tile":true,"profile_image_url":"http:\/\/pbs.twimg.com\/profile_images\/620540450500419584\/HHkre3eX_normal.jpg","profile_image_url_https":"https:\/\/pbs.twimg.com\/profile_images\/620540450500419584\/HHkre3eX_normal.jpg","profile_banner_url":"https:\/\/pbs.twimg.com\/profile_banners\/104534121\/1420379970","profile_link_color":"000000","profile_sidebar_border_color":"FFFFFF","profile_sidebar_fill_color":"E6F6F9","profile_text_color":"333333","profile_use_background_image":true,"has_extended_profile":false,"default_profile":false,"default_profile_image":false,"following":false,"follow_request_sent":false,"notifications":false,"translator_type":"none"},"geo":null,"coordinates":null,"place":null,"contributors":null,"is_quote_status":false,"retweet_count":0,"favorite_count":0,"favorited":false,"retweeted":false,"possibly_sensitive":false,"lang":"en"},{"created_at":"Thu Jan 19 14:27:13 +0000 2017","id":822088026209812480,"id_str":"822088026209812480","text":"A new favorite: Why You Gotta Act Like That? [ft Fumin, Black The Ripper, Faction G &amp; Lady Lykez] by <a href="http://www.twitter.com/ScratchaDVA">@ScratchaDVA</a> https:\/\/t.co\/irK7ucSaHq","truncated":false,"entities":{"hashtags":[],"symbols":[],"user_mentions":[{"screen_name":"ScratchaDVA","name":"Scratcha DVA","id":21656200,"id_str":"21656200","indices":[105,117]}],"urls":[{"url":"https:\/\/t.co\/irK7ucSaHq","expanded_url":"https:\/\/soundcloud.com\/scratchadva\/why-you-gotta-act-like-that-ft-fumin-black-the-ripper-faction-g-lady-lykez","display_url":"soundcloud.com\/scratchadva\/wh\u2026","indices":[118,141]}]},"source":"\u003ca href=\"http:\/\/soundcloud.com\" rel=\"nofollow\"\u003eSoundCloud\u003c\/a\u003e","in_reply_to_status_id":null,"in_reply_to_status_id_str":null,"in_reply_to_user_id":null,"in_reply_to_user_id_str":null,"in_reply_to_screen_name":null,"user":{"id":104534121,"id_str":"104534121","name":"Insert","screen_name":"WeAreInsert","location":"London","description":"Insert is a virtual platform which uses audio, visual & textual formats to push and contextualise select areas of underground music. <a href="http://www.twitter.com/VICE">@VICE</a> | <a href="http://www.twitter.com/NTSlive">@NTSlive</a>","url":"https:\/\/t.co\/06GZVcXiJV","entities":{"url":{"urls":[{"url":"https:\/\/t.co\/06GZVcXiJV","expanded_url":"http:\/\/weareinsert.com","display_url":"weareinsert.com","indices":[0,23]}]},"description":{"urls":[]}},"protected":false,"followers_count":1328,"friends_count":845,"listed_count":23,"created_at":"Wed Jan 13 16:35:55 +0000 2010","favourites_count":1123,"utc_offset":0,"time_zone":"London","geo_enabled":true,"verified":false,"statuses_count":4780,"lang":"en","contributors_enabled":false,"is_translator":false,"is_translation_enabled":false,"profile_background_color":"000000","profile_background_image_url":"http:\/\/pbs.twimg.com\/profile_background_images\/551739826647490560\/p5wNFMMU.jpeg","profile_background_image_url_https":"https:\/\/pbs.twimg.com\/profile_background_images\/551739826647490560\/p5wNFMMU.jpeg","profile_background_tile":true,"profile_image_url":"http:\/\/pbs.twimg.com\/profile_images\/620540450500419584\/HHkre3eX_normal.jpg","profile_image_url_https":"https:\/\/pbs.twimg.com\/profile_images\/620540450500419584\/HHkre3eX_normal.jpg","profile_banner_url":"https:\/\/pbs.twimg.com\/profile_banners\/104534121\/1420379970","profile_link_color":"000000","profile_sidebar_border_color":"FFFFFF","profile_sidebar_fill_color":"E6F6F9","profile_text_color":"333333","profile_use_background_image":true,"has_extended_profile":false,"default_profile":false,"default_profile_image":false,"following":false,"follow_request_sent":false,"notifications":false,"translator_type":"none"},"geo":null,"coordinates":null,"place":null,"contributors":null,"is_quote_status":false,"retweet_count":0,"favorite_count":2,"favorited":false,"retweeted":false,"possibly_sensitive":false,"lang":"en"},{"created_at":"Thu Jan 19 14:07:37 +0000 2017","id":822083090923274240,"id_str":"822083090923274240","text":"You can now stream &amp; download our latest <a href="http://www.twitter.com/NTSlive">@NTSlive</a> show here:\nhttps:\/\/t.co\/8oGT7AkJ50\n\nIncluding full track listing. https:\/\/t.co\/pQdvDcqpuG","truncated":false,"entities":{"hashtags":[],"symbols":[],"user_mentions":[{"screen_name":"NTSlive","name":"NTS Radio","id":240439135,"id_str":"240439135","indices":[45,53]}],"urls":[{"url":"https:\/\/t.co\/8oGT7AkJ50","expanded_url":"https:\/\/weareinsert.com\/audio\/insert-nts-january-2017\/","display_url":"weareinsert.com\/audio\/insert-n\u2026","indices":[65,88]}],"media":[{"id":822083087752372224,"id_str":"822083087752372224","indices":[120,143],"media_url":"http:\/\/pbs.twimg.com\/media\/C2igNnVWIAAJUcL.jpg","media_url_https":"https:\/\/pbs.twimg.com\/media\/C2igNnVWIAAJUcL.jpg","url":"https:\/\/t.co\/pQdvDcqpuG","display_url":"pic.twitter.com\/pQdvDcqpuG","expanded_url":"https:\/\/twitter.com\/WeAreInsert\/status\/822083090923274240\/photo\/1","type":"photo","sizes":{"medium":{"w":1200,"h":675,"resize":"fit"},"large":{"w":1920,"h":1080,"resize":"fit"},"small":{"w":680,"h":383,"resize":"fit"},"thumb":{"w":150,"h":150,"resize":"crop"}}}]},"extended_entities":{"media":[{"id":822083087752372224,"id_str":"822083087752372224","indices":[120,143],"media_url":"http:\/\/pbs.twimg.com\/media\/C2igNnVWIAAJUcL.jpg","media_url_https":"https:\/\/pbs.twimg.com\/media\/C2igNnVWIAAJUcL.jpg","url":"https:\/\/t.co\/pQdvDcqpuG","display_url":"pic.twitter.com\/pQdvDcqpuG","expanded_url":"https:\/\/twitter.com\/WeAreInsert\/status\/822083090923274240\/photo\/1","type":"photo","sizes":{"medium":{"w":1200,"h":675,"resize":"fit"},"large":{"w":1920,"h":1080,"resize":"fit"},"small":{"w":680,"h":383,"resize":"fit"},"thumb":{"w":150,"h":150,"resize":"crop"}}}]},"source":"\u003ca href=\"http:\/\/itunes.apple.com\/us\/app\/twitter\/id409789998?mt=12\" rel=\"nofollow\"\u003eTwitter for Mac\u003c\/a\u003e","in_reply_to_status_id":null,"in_reply_to_status_id_str":null,"in_reply_to_user_id":null,"in_reply_to_user_id_str":null,"in_reply_to_screen_name":null,"user":{"id":104534121,"id_str":"104534121","name":"Insert","screen_name":"WeAreInsert","location":"London","description":"Insert is a virtual platform which uses audio, visual & textual formats to push and contextualise select areas of underground music. <a href="http://www.twitter.com/VICE">@VICE</a> | <a href="http://www.twitter.com/NTSlive">@NTSlive</a>","url":"https:\/\/t.co\/06GZVcXiJV","entities":{"url":{"urls":[{"url":"https:\/\/t.co\/06GZVcXiJV","expanded_url":"http:\/\/weareinsert.com","display_url":"weareinsert.com","indices":[0,23]}]},"description":{"urls":[]}},"protected":false,"followers_count":1328,"friends_count":845,"listed_count":23,"created_at":"Wed Jan 13 16:35:55 +0000 2010","favourites_count":1123,"utc_offset":0,"time_zone":"London","geo_enabled":true,"verified":false,"statuses_count":4780,"lang":"en","contributors_enabled":false,"is_translator":false,"is_translation_enabled":false,"profile_background_color":"000000","profile_background_image_url":"http:\/\/pbs.twimg.com\/profile_background_images\/551739826647490560\/p5wNFMMU.jpeg","profile_background_image_url_https":"https:\/\/pbs.twimg.com\/profile_background_images\/551739826647490560\/p5wNFMMU.jpeg","profile_background_tile":true,"profile_image_url":"http:\/\/pbs.twimg.com\/profile_images\/620540450500419584\/HHkre3eX_normal.jpg","profile_image_url_https":"https:\/\/pbs.twimg.com\/profile_images\/620540450500419584\/HHkre3eX_normal.jpg","profile_banner_url":"https:\/\/pbs.twimg.com\/profile_banners\/104534121\/1420379970","profile_link_color":"000000","profile_sidebar_border_color":"FFFFFF","profile_sidebar_fill_color":"E6F6F9","profile_text_color":"333333","profile_use_background_image":true,"has_extended_profile":false,"default_profile":false,"default_profile_image":false,"following":false,"follow_request_sent":false,"notifications":false,"translator_type":"none"},"geo":null,"coordinates":null,"place":null,"contributors":null,"is_quote_status":false,"retweet_count":1,"favorite_count":2,"favorited":false,"retweeted":false,"possibly_sensitive":false,"lang":"en"},{"created_at":"Wed Jan 18 16:15:20 +0000 2017","id":821752845758320640,"id_str":"821752845758320640","text":"RT <a href="http://www.twitter.com/Pitch">@Pitch</a>_Rider: Out to <a href="http://www.twitter.com/WeAreInsert">@WeAreInsert</a> for spinning DJ DVD RIP's 'STEALTHBUILD' on <a href="http://www.twitter.com/NTSlive">@NTSlive</a> last night. Out next week on <a href="http://www.twitter.com/Pr">@Pr</a>_JKTs https:\/\/t.c\u2026","truncated":false,"entities":{"hashtags":[],"symbols":[],"user_mentions":[{"screen_name":"Pitch_Rider","name":"Pitch Rider","id":1262632633,"id_str":"1262632633","indices":[3,15]},{"screen_name":"WeAreInsert","name":"Insert","id":104534121,"id_str":"104534121","indices":[24,36]},{"screen_name":"NTSlive","name":"NTS Radio","id":240439135,"id_str":"240439135","indices":[81,89]},{"screen_name":"Pr_JKTs","name":"Prjkts","id":3304555617,"id_str":"3304555617","indices":[119,127]}],"urls":[]},"source":"\u003ca href=\"http:\/\/itunes.apple.com\/us\/app\/twitter\/id409789998?mt=12\" rel=\"nofollow\"\u003eTwitter for Mac\u003c\/a\u003e","in_reply_to_status_id":null,"in_reply_to_status_id_str":null,"in_reply_to_user_id":null,"in_reply_to_user_id_str":null,"in_reply_to_screen_name":null,"user":{"id":104534121,"id_str":"104534121","name":"Insert","screen_name":"WeAreInsert","location":"London","description":"Insert is a virtual platform which uses audio, visual & textual formats to push and contextualise select areas of underground music. <a href="http://www.twitter.com/VICE">@VICE</a> | <a href="http://www.twitter.com/NTSlive">@NTSlive</a>","url":"https:\/\/t.co\/06GZVcXiJV","entities":{"url":{"urls":[{"url":"https:\/\/t.co\/06GZVcXiJV","expanded_url":"http:\/\/weareinsert.com","display_url":"weareinsert.com","indices":[0,23]}]},"description":{"urls":[]}},"protected":false,"followers_count":1328,"friends_count":845,"listed_count":23,"created_at":"Wed Jan 13 16:35:55 +0000 2010","favourites_count":1123,"utc_offset":0,"time_zone":"London","geo_enabled":true,"verified":false,"statuses_count":4780,"lang":"en","contributors_enabled":false,"is_translator":false,"is_translation_enabled":false,"profile_background_color":"000000","profile_background_image_url":"http:\/\/pbs.twimg.com\/profile_background_images\/551739826647490560\/p5wNFMMU.jpeg","profile_background_image_url_https":"https:\/\/pbs.twimg.com\/profile_background_images\/551739826647490560\/p5wNFMMU.jpeg","profile_background_tile":true,"profile_image_url":"http:\/\/pbs.twimg.com\/profile_images\/620540450500419584\/HHkre3eX_normal.jpg","profile_image_url_https":"https:\/\/pbs.twimg.com\/profile_images\/620540450500419584\/HHkre3eX_normal.jpg","profile_banner_url":"https:\/\/pbs.twimg.com\/profile_banners\/104534121\/1420379970","profile_link_color":"000000","profile_sidebar_border_color":"FFFFFF","profile_sidebar_fill_color":"E6F6F9","profile_text_color":"333333","profile_use_background_image":true,"has_extended_profile":false,"default_profile":false,"default_profile_image":false,"following":false,"follow_request_sent":false,"notifications":false,"translator_type":"none"},"geo":null,"coordinates":null,"place":null,"contributors":null,"retweeted_status":{"created_at":"Wed Jan 18 15:52:30 +0000 2017","id":821747099784056832,"id_str":"821747099784056832","text":"Out to <a href="http://www.twitter.com/WeAreInsert">@WeAreInsert</a> for spinning DJ DVD RIP's 'STEALTHBUILD' on <a href="http://www.twitter.com/NTSlive">@NTSlive</a> last night. Out next week on <a href="http://www.twitter.com/Pr">@Pr</a>_JKTs https:\/\/t.co\/02Lb6KHB8E","truncated":false,"entities":{"hashtags":[],"symbols":[],"user_mentions":[{"screen_name":"WeAreInsert","name":"Insert","id":104534121,"id_str":"104534121","indices":[7,19]},{"screen_name":"NTSlive","name":"NTS Radio","id":240439135,"id_str":"240439135","indices":[64,72]},{"screen_name":"Pr_JKTs","name":"Prjkts","id":3304555617,"id_str":"3304555617","indices":[102,110]}],"urls":[{"url":"https:\/\/t.co\/02Lb6KHB8E","expanded_url":"http:\/\/www.nts.live\/shows\/insert\/episodes\/insert-17th-january-2017","display_url":"nts.live\/shows\/insert\/e\u2026","indices":[111,134]}]},"source":"\u003ca href=\"http:\/\/twitter.com\" rel=\"nofollow\"\u003eTwitter Web Client\u003c\/a\u003e","in_reply_to_status_id":null,"in_reply_to_status_id_str":null,"in_reply_to_user_id":null,"in_reply_to_user_id_str":null,"in_reply_to_screen_name":null,"user":{"id":1262632633,"id_str":"1262632633","name":"Pitch Rider","screen_name":"Pitch_Rider","location":"South UK","description":"Professional PR & distribution for underground record labels & artists. \n\nhttps:\/\/t.co\/KqGfRo2oJP\nhttps:\/\/t.co\/pfrYCiqFwl","url":"http:\/\/t.co\/87rWdLxYqj","entities":{"url":{"urls":[{"url":"http:\/\/t.co\/87rWdLxYqj","expanded_url":"http:\/\/www.pitchrider.co.uk","display_url":"pitchrider.co.uk","indices":[0,22]}]},"description":{"urls":[{"url":"https:\/\/t.co\/KqGfRo2oJP","expanded_url":"https:\/\/soundcloud.com\/pitchridermusic","display_url":"soundcloud.com\/pitchridermusic","indices":[74,97]},{"url":"https:\/\/t.co\/pfrYCiqFwl","expanded_url":"https:\/\/www.youtube.com\/user\/PitchRiderUK","display_url":"youtube.com\/user\/PitchRide\u2026","indices":[98,121]}]}},"protected":false,"followers_count":1893,"friends_count":2287,"listed_count":27,"created_at":"Tue Mar 12 18:47:32 +0000 2013","favourites_count":899,"utc_offset":0,"time_zone":"Casablanca","geo_enabled":false,"verified":false,"statuses_count":1350,"lang":"en","contributors_enabled":false,"is_translator":false,"is_translation_enabled":false,"profile_background_color":"020D0C","profile_background_image_url":"http:\/\/pbs.twimg.com\/profile_background_images\/378800000176029963\/1yyvHv3F.jpeg","profile_background_image_url_https":"https:\/\/pbs
